<w:tc>
	<w:tcPr>
		<w:tcW w:w="1704" w:type="dxa"/>
		<w:shd w:val="clear" w:color="auto" w:fill="D2EAF1"/>
		<w:noWrap/>
		<w:vAlign w:val="center"/>
	</w:tcPr>
	<w:p w14:paraId="4F7411E5" w14:textId="77777777" w:rsidR="0030108B" w:rsidRPr="0030108B" w:rsidRDefault="0030108B" w:rsidP="0030108B">
		<w:pPr>
			<w:widowControl/>
			<w:jc w:val="center"/>
			<w:rPr>
				<w:rFonts w:ascii="宋体" w:cs="Arial"/>
				<w:kern w:val="0"/>
				<w:szCs w:val="21"/>
			</w:rPr>
		</w:pPr>
		<w:r w:rsidRPr="0030108B">
			<w:rPr>
				<w:rFonts w:ascii="宋体" w:cs="Arial" w:hint="eastAsia"/>
				<w:kern w:val="0"/>
				<w:szCs w:val="21"/>
			</w:rPr>
			<w:t>${value}</w:t>
		</w:r>
	</w:p>
</w:tc>